evaluate_dfs/__init__.py
evaluate_dfs/dfs_evaluator.py
evaluate_dfs/match.py
evaluate_dfs/series_evaluator.py
evaluate_dfs-0.0.2.dist-info/LICENSE
evaluate_dfs-0.0.2.dist-info/METADATA
evaluate_dfs-0.0.2.dist-info/WHEEL
evaluate_dfs-0.0.2.dist-info/top_level.txt
evaluate_dfs-0.0.2.dist-info/RECORD
