Metadata-Version: 2.1
Name: evaluate-dfs
Version: 0.0.2
Summary: Provides features to evaluate a series or dataframe against another series or dataframe.
Home-page: https://github.com/yohan10/evaluate-dfs
Author: Yohan Kim
Author-email: yohankimchi@gmail.com
License: BSD
Classifier: License :: OSI Approved :: BSD License
Classifier: Programming Language :: Python
Classifier: Programming Language :: Python :: 3
Classifier: Programming Language :: Python :: 3 :: Only
Requires-Python: >=3.8
License-File: LICENSE
Requires-Dist: pandas (>=1.4.2)
Requires-Dist: pandarallel (>=1.6.1)
Provides-Extra: dev
Requires-Dist: numpy (>=1.22.4) ; extra == 'dev'
